{"rows":11,"cols":11,"words":["WOODCHUCK","CLOWNFISH","COCKATOO","SAILFISH","CAPYBERA","MARMOSET","WARTHOG","BIVALVE","BULLDOG","TARPON","CHITON","SHREW","DINGO"],"boardCharacters":[["K","A","F","E","V","L","A","V","I","B","S"],["C","R","J","T","E","S","O","M","R","A","M"],["U","E","M","D","I","N","G","O","C","W","S"],["H","B","S","F","P","Z","G","L","C","A","H"],["C","Y","Z","E","S","O","O","O","C","R","R"],["D","P","L","G","D","W","C","N","H","T","E"],["O","A","J","L","N","K","O","Z","I","H","W"],["O","C","L","F","A","P","S","I","T","O","X"],["W","U","I","T","R","V","F","V","O","G","P"],["B","S","O","A","Z","V","S","C","N","J","R"],["H","O","T","S","A","I","L","F","I","S","H"]],"wordPlacements":[{"word":"WOODCHUCK","row":8,"col":0,"h":0,"v":-1},{"word":"CLOWNFISH","row":2,"col":8,"h":-1,"v":1},{"word":"COCKATOO","row":3,"col":8,"h":-1,"v":1},{"word":"SAILFISH","row":10,"col":3,"h":1,"v":0},{"word":"CAPYBERA","row":7,"col":1,"h":0,"v":-1},{"word":"MARMOSET","row":1,"col":10,"h":-1,"v":0},{"word":"WARTHOG","row":2,"col":9,"h":0,"v":1},{"word":"BIVALVE","row":0,"col":9,"h":-1,"v":0},{"word":"BULLDOG","row":9,"col":0,"h":1,"v":-1},{"word":"TARPON","row":10,"col":2,"h":1,"v":-1},{"word":"CHITON","row":4,"col":8,"h":0,"v":1},{"word":"SHREW","row":2,"col":10,"h":0,"v":1},{"word":"DINGO","row":2,"col":3,"h":1,"v":0}]}