{"rows":9,"cols":9,"words":["CANDLE","GLOVES","CHILLS","BERET","POLAR","WINDY","STORM","STOVE","WOOL","SLED","COLD","SKI","FLU","CAP"],"boardCharacters":[["G","C","H","I","L","L","S","S","G"],["L","E","R","S","L","E","D","T","L"],["O","T","E","R","E","B","Z","O","O"],["O","Y","P","A","C","V","B","R","V"],["W","I","D","O","Y","U","O","M","E"],["E","C","L","F","L","D","S","T","S"],["M","O","M","L","O","A","N","K","S"],["Y","L","K","U","Z","N","R","I","I"],["Q","D","E","L","D","N","A","C","W"]],"wordPlacements":[{"word":"CANDLE","row":8,"col":7,"h":-1,"v":0},{"word":"GLOVES","row":0,"col":8,"h":0,"v":1},{"word":"CHILLS","row":0,"col":1,"h":1,"v":0},{"word":"BERET","row":2,"col":5,"h":-1,"v":0},{"word":"POLAR","row":3,"col":2,"h":1,"v":1},{"word":"WINDY","row":8,"col":8,"h":-1,"v":-1},{"word":"STORM","row":0,"col":7,"h":0,"v":1},{"word":"STOVE","row":6,"col":8,"h":-1,"v":-1},{"word":"WOOL","row":4,"col":0,"h":0,"v":-1},{"word":"SLED","row":1,"col":3,"h":1,"v":0},{"word":"COLD","row":5,"col":1,"h":0,"v":1},{"word":"SKI","row":5,"col":6,"h":1,"v":1},{"word":"FLU","row":5,"col":3,"h":0,"v":1},{"word":"CAP","row":3,"col":4,"h":-1,"v":0}]}