{"rows":9,"cols":9,"words":["PARTNER","RETIRE","LEADER","WORKER","BAKER","OFFER","PILOT","JUDGE","MODEL","APPLY","TASK","CHEF"],"boardCharacters":[["E","L","E","D","O","M","O","F","I"],["M","O","F","F","E","R","B","P","Y"],["W","R","C","R","F","E","I","L","R"],["O","M","Q","E","B","L","P","L","J"],["R","N","H","A","O","P","W","E","U"],["K","C","K","T","A","K","A","A","D"],["E","E","I","E","F","S","O","D","G"],["R","E","N","T","R","A","P","E","E"],["R","Z","D","R","E","T","I","R","E"]],"wordPlacements":[{"word":"PARTNER","row":7,"col":6,"h":-1,"v":0},{"word":"RETIRE","row":8,"col":3,"h":1,"v":0},{"word":"LEADER","row":3,"col":7,"h":0,"v":1},{"word":"WORKER","row":2,"col":0,"h":0,"v":1},{"word":"BAKER","row":3,"col":4,"h":-1,"v":1},{"word":"OFFER","row":1,"col":1,"h":1,"v":0},{"word":"PILOT","row":1,"col":7,"h":-1,"v":1},{"word":"JUDGE","row":3,"col":8,"h":0,"v":1},{"word":"MODEL","row":0,"col":5,"h":-1,"v":0},{"word":"APPLY","row":5,"col":4,"h":1,"v":-1},{"word":"TASK","row":8,"col":5,"h":0,"v":-1},{"word":"CHEF","row":5,"col":1,"h":1,"v":-1}]}