{"rows":11,"cols":11,"words":["PORTRAIT","PORTRAY","SOLVENT","ARTWORK","VARNISH","CASTING","STENCIL","PIGMENT","POTTERY","CANVAS","POUNCE","PRINT","SHADE","WOOD","TUBE"],"boardCharacters":[["P","V","H","P","P","O","R","T","R","A","Y"],["O","Y","S","R","S","O","L","V","E","N","T"],["T","A","I","I","G","J","U","M","U","E","N"],["T","S","N","N","N","N","T","N","B","Y","E"],["E","T","R","T","S","D","I","U","C","Q","M"],["R","E","A","G","O","A","T","T","G","E","G"],["Y","N","V","O","D","I","V","D","S","F","I"],["C","C","W","U","A","K","H","N","E","A","P"],["T","I","A","R","T","R","O","P","A","G","C"],["J","L","A","R","T","W","O","R","K","C","N"],["F","Q","U","E","D","A","H","S","X","M","F"]],"wordPlacements":[{"word":"PORTRAIT","row":8,"col":7,"h":-1,"v":0},{"word":"PORTRAY","row":0,"col":4,"h":1,"v":0},{"word":"SOLVENT","row":1,"col":4,"h":1,"v":0},{"word":"ARTWORK","row":9,"col":2,"h":1,"v":0},{"word":"VARNISH","row":6,"col":2,"h":0,"v":-1},{"word":"CASTING","row":8,"col":10,"h":-1,"v":-1},{"word":"STENCIL","row":3,"col":1,"h":0,"v":1},{"word":"PIGMENT","row":7,"col":10,"h":0,"v":-1},{"word":"POTTERY","row":0,"col":0,"h":0,"v":1},{"word":"CANVAS","row":9,"col":9,"h":-1,"v":-1},{"word":"POUNCE","row":0,"col":4,"h":1,"v":1},{"word":"PRINT","row":0,"col":3,"h":0,"v":1},{"word":"SHADE","row":10,"col":7,"h":-1,"v":0},{"word":"WOOD","row":7,"col":2,"h":1,"v":-1},{"word":"TUBE","row":5,"col":6,"h":1,"v":-1}]}