{"rows":6,"cols":6,"words":["PENNY","MONEY","CHECK","YIELD","VAULT","SAVE","POOR"],"boardCharacters":[["P","E","N","N","Y","W"],["Y","Y","P","O","O","R"],["I","K","C","E","H","C"],["E","M","O","N","E","Y"],["L","E","V","A","S","M"],["D","T","L","U","A","V"]],"wordPlacements":[{"word":"PENNY","row":0,"col":0,"h":1,"v":0},{"word":"MONEY","row":3,"col":1,"h":1,"v":0},{"word":"CHECK","row":2,"col":5,"h":-1,"v":0},{"word":"YIELD","row":1,"col":0,"h":0,"v":1},{"word":"VAULT","row":5,"col":5,"h":-1,"v":0},{"word":"SAVE","row":4,"col":4,"h":-1,"v":0},{"word":"POOR","row":1,"col":2,"h":1,"v":0}]}