{"rows":10,"cols":10,"words":["CAPTURE","GALLEON","SWAGGER","SILVER","PEGLEG","PISTOL","MUTINY","RICHES","BOUNTY","MATES","SEAS","DECK","GOLD","SAIL","GUN"],"boardCharacters":[["N","S","H","S","P","E","G","L","E","G"],["O","E","P","I","S","T","O","L","Y","T"],["E","H","U","M","H","A","E","K","T","S"],["L","C","R","G","U","R","B","C","N","I"],["L","I","K","E","U","T","U","E","U","L"],["A","R","A","T","G","N","I","D","O","V"],["G","S","P","S","O","G","L","N","B","E"],["S","A","E","S","L","V","A","Z","Y","R"],["C","T","N","J","D","Z","G","W","S","Y"],["J","Z","T","M","A","T","E","S","S","T"]],"wordPlacements":[{"word":"CAPTURE","row":8,"col":0,"h":1,"v":-1},{"word":"GALLEON","row":6,"col":0,"h":0,"v":-1},{"word":"SWAGGER","row":9,"col":8,"h":-1,"v":-1},{"word":"SILVER","row":2,"col":9,"h":0,"v":1},{"word":"PEGLEG","row":0,"col":4,"h":1,"v":0},{"word":"PISTOL","row":1,"col":2,"h":1,"v":0},{"word":"MUTINY","row":2,"col":3,"h":1,"v":1},{"word":"RICHES","row":5,"col":1,"h":0,"v":-1},{"word":"BOUNTY","row":6,"col":8,"h":0,"v":-1},{"word":"MATES","row":9,"col":3,"h":1,"v":0},{"word":"SEAS","row":7,"col":3,"h":-1,"v":0},{"word":"DECK","row":5,"col":7,"h":0,"v":-1},{"word":"GOLD","row":5,"col":4,"h":0,"v":1},{"word":"SAIL","row":6,"col":3,"h":-1,"v":-1},{"word":"GUN","row":3,"col":3,"h":1,"v":1}]}