{"rows":11,"cols":11,"words":["RUTHLESS","VIOLENCE","PLUNDER","ROBBER","CANNON","JEWELS","SCURVY","RICHES","BARREL","GIBBET","BANDIT","CRUEL","SWORD","TIDES","THUG","AHOY","MAP"],"boardCharacters":[["L","E","R","R","A","B","T","A","P","A","M"],["R","K","I","D","O","N","K","H","R","X","B"],["O","T","Q","S","J","Y","V","R","U","C","S"],["B","E","U","S","W","V","X","Z","T","G","E"],["B","B","Y","E","T","O","R","V","H","S","C"],["E","B","O","C","T","I","R","D","L","L","N"],["R","I","H","N","R","I","D","D","E","E","E"],["V","G","A","R","U","U","D","E","S","W","L"],["R","I","C","H","E","S","E","N","S","E","O"],["G","C","A","N","N","O","N","L","A","J","I"],["E","R","E","D","N","U","L","P","O","B","V"]],"wordPlacements":[{"word":"RUTHLESS","row":1,"col":8,"h":0,"v":1},{"word":"VIOLENCE","row":10,"col":10,"h":0,"v":-1},{"word":"PLUNDER","row":10,"col":7,"h":-1,"v":0},{"word":"ROBBER","row":1,"col":0,"h":0,"v":1},{"word":"CANNON","row":9,"col":1,"h":1,"v":0},{"word":"JEWELS","row":9,"col":9,"h":0,"v":-1},{"word":"SCURVY","row":2,"col":10,"h":-1,"v":0},{"word":"RICHES","row":8,"col":0,"h":1,"v":0},{"word":"BARREL","row":0,"col":5,"h":-1,"v":0},{"word":"GIBBET","row":7,"col":1,"h":0,"v":-1},{"word":"BANDIT","row":10,"col":9,"h":-1,"v":-1},{"word":"CRUEL","row":5,"col":3,"h":1,"v":1},{"word":"SWORD","row":2,"col":3,"h":1,"v":1},{"word":"TIDES","row":4,"col":4,"h":1,"v":1},{"word":"THUG","row":0,"col":6,"h":1,"v":1},{"word":"AHOY","row":7,"col":2,"h":0,"v":-1},{"word":"MAP","row":0,"col":10,"h":-1,"v":0}]}