{"rows":12,"cols":12,"words":["PATIENT","ENVIOUS","STRETCH","GRUMPY","STROKE","CLEVER","POLITE","SLEEP","SHOUT","SQUAT","DRINK","PLANT","CATCH","QUIET","READ","STOP","PLAY","COLD","LIFT","PICK","LICK","DIVE","WASH"],"boardCharacters":[["G","W","E","L","S","V","D","L","A","B","S","B"],["R","A","H","I","H","L","A","W","I","I","L","V"],["U","S","S","U","O","I","V","N","E","C","B","K"],["M","H","P","C","U","U","S","T","R","O","K","E"],["P","H","O","U","T","P","D","P","I","C","K","M"],["Y","C","L","B","T","A","L","Q","V","S","T","F"],["C","T","I","S","E","X","U","A","G","A","E","M"],["A","E","T","R","T","D","D","Q","N","L","I","P"],["T","R","E","P","T","O","I","R","S","T","U","E"],["C","T","F","I","L","D","P","V","I","B","Q","E"],["H","S","N","W","P","A","T","I","E","N","T","L"],["R","E","V","E","L","C","Y","W","Z","E","K","S"]],"wordPlacements":[{"word":"PATIENT","row":10,"col":4,"h":1,"v":0},{"word":"ENVIOUS","row":2,"col":8,"h":-1,"v":0},{"word":"STRETCH","row":10,"col":1,"h":0,"v":-1},{"word":"GRUMPY","row":0,"col":0,"h":0,"v":1},{"word":"STROKE","row":3,"col":6,"h":1,"v":0},{"word":"CLEVER","row":11,"col":5,"h":-1,"v":0},{"word":"POLITE","row":3,"col":2,"h":0,"v":1},{"word":"SLEEP","row":11,"col":11,"h":0,"v":-1},{"word":"SHOUT","row":0,"col":4,"h":0,"v":1},{"word":"SQUAT","row":8,"col":8,"h":-1,"v":-1},{"word":"DRINK","row":7,"col":6,"h":1,"v":1},{"word":"PLANT","row":4,"col":5,"h":1,"v":1},{"word":"CATCH","row":6,"col":0,"h":0,"v":1},{"word":"QUIET","row":9,"col":10,"h":0,"v":-1},{"word":"READ","row":7,"col":3,"h":1,"v":-1},{"word":"STOP","row":6,"col":3,"h":1,"v":1},{"word":"PLAY","row":8,"col":3,"h":1,"v":1},{"word":"COLD","row":3,"col":3,"h":1,"v":-1},{"word":"LIFT","row":9,"col":4,"h":-1,"v":0},{"word":"PICK","row":4,"col":7,"h":1,"v":0},{"word":"LICK","row":0,"col":7,"h":1,"v":1},{"word":"DIVE","row":7,"col":5,"h":1,"v":1},{"word":"WASH","row":0,"col":1,"h":0,"v":1}]}