{"rows":6,"cols":6,"words":["BOOTS","CAUSE","RADIO","BADGE","CRAWL","PUMP","HOSE"],"boardCharacters":[["S","P","U","M","P","Q"],["T","B","Q","I","E","O"],["O","C","A","S","I","H"],["O","V","U","D","V","O"],["B","A","A","Q","G","S"],["C","R","A","W","L","E"]],"wordPlacements":[{"word":"BOOTS","row":4,"col":0,"h":0,"v":-1},{"word":"CAUSE","row":5,"col":0,"h":1,"v":-1},{"word":"RADIO","row":5,"col":1,"h":1,"v":-1},{"word":"BADGE","row":1,"col":1,"h":1,"v":1},{"word":"CRAWL","row":5,"col":0,"h":1,"v":0},{"word":"PUMP","row":0,"col":1,"h":1,"v":0},{"word":"HOSE","row":2,"col":5,"h":0,"v":1}]}