{"rows":13,"cols":13,"words":["PROTOCOL","ETHERNET","COMPUTER","GATEWAY","RESTORE","TEMINAL","PROGRAM","PASSIVE","BRIDGE","THREAD","REBOOT","BITMAP","ANALOG","MIRROR","OPTION","BLOG","TEXT","PAGE","BUS","WWW","LAN"],"boardCharacters":[["K","E","P","R","M","A","R","G","O","R","P","J","V"],["A","T","G","R","E","T","U","P","M","O","C","J","C"],["N","H","R","O","T","E","V","I","S","S","A","P","M"],["A","E","E","E","L","X","X","L","H","F","D","P","L"],["L","R","B","B","G","B","E","V","O","A","R","A","A"],["O","N","O","N","I","A","E","T","S","O","N","R","N"],["G","E","O","R","E","T","P","B","T","T","K","K","I"],["E","T","T","E","R","N","M","O","W","H","L","N","M"],["V","Q","B","S","K","I","C","A","N","R","B","W","E"],["N","O","I","T","P","O","M","K","P","E","U","B","T"],["E","P","Y","O","L","Q","H","W","G","A","S","Y","Z"],["J","S","B","R","I","D","G","E","W","D","R","S","N"],["Y","R","T","E","J","G","A","T","E","W","A","Y","H"]],"wordPlacements":[{"word":"PROTOCOL","row":3,"col":11,"h":-1,"v":1},{"word":"ETHERNET","row":0,"col":1,"h":0,"v":1},{"word":"COMPUTER","row":1,"col":10,"h":-1,"v":0},{"word":"GATEWAY","row":12,"col":5,"h":1,"v":0},{"word":"RESTORE","row":6,"col":3,"h":0,"v":1},{"word":"TEMINAL","row":9,"col":12,"h":0,"v":-1},{"word":"PROGRAM","row":0,"col":10,"h":-1,"v":0},{"word":"PASSIVE","row":2,"col":11,"h":-1,"v":0},{"word":"BRIDGE","row":11,"col":2,"h":1,"v":0},{"word":"THREAD","row":6,"col":9,"h":0,"v":1},{"word":"REBOOT","row":2,"col":2,"h":0,"v":1},{"word":"BITMAP","row":4,"col":3,"h":1,"v":1},{"word":"ANALOG","row":1,"col":0,"h":0,"v":1},{"word":"MIRROR","row":9,"col":6,"h":-1,"v":-1},{"word":"OPTION","row":9,"col":5,"h":-1,"v":0},{"word":"BLOG","row":4,"col":5,"h":-1,"v":-1},{"word":"TEXT","row":5,"col":7,"h":-1,"v":-1},{"word":"PAGE","row":6,"col":6,"h":-1,"v":-1},{"word":"BUS","row":8,"col":10,"h":0,"v":1},{"word":"WWW","row":12,"col":9,"h":-1,"v":-1},{"word":"LAN","row":3,"col":12,"h":-1,"v":1}]}