{"rows":12,"cols":12,"words":["TYPEFACE","SNAPSHOT","PHISHING","TRAFFIC","ADAPTER","LATENCY","CAPTCHA","ROUTER","UPLOAD","WIDGET","TABLE","LINUX","VIRUS","BLOG","SAVE","WWW","BUS","APP"],"boardCharacters":[["E","C","A","P","T","C","H","A","P","L","T","R"],["L","T","Q","J","N","T","L","H","Z","T","E","S"],["I","D","T","W","E","R","I","P","Y","T","S","T"],["N","G","W","G","E","S","T","P","P","U","N","R"],["U","J","D","T","H","L","E","A","R","S","A","A"],["X","I","U","I","S","F","D","I","P","U","P","F"],["W","O","N","G","A","A","V","W","T","B","S","F"],["R","G","W","C","V","B","G","O","L","B","H","I"],["T","Z","E","Z","E","F","X","G","W","C","O","C"],["J","U","S","U","P","L","O","A","D","L","T","B"],["P","W","W","W","L","A","T","E","N","C","Y","X"],["N","X","F","Q","L","W","U","E","L","B","A","T"]],"wordPlacements":[{"word":"TYPEFACE","row":1,"col":9,"h":-1,"v":1},{"word":"SNAPSHOT","row":2,"col":10,"h":0,"v":1},{"word":"PHISHING","row":0,"col":8,"h":-1,"v":1},{"word":"TRAFFIC","row":2,"col":11,"h":0,"v":1},{"word":"ADAPTER","row":6,"col":5,"h":1,"v":-1},{"word":"LATENCY","row":10,"col":4,"h":1,"v":0},{"word":"CAPTCHA","row":0,"col":1,"h":1,"v":0},{"word":"ROUTER","row":7,"col":0,"h":1,"v":-1},{"word":"UPLOAD","row":9,"col":3,"h":1,"v":0},{"word":"WIDGET","row":6,"col":0,"h":1,"v":-1},{"word":"TABLE","row":11,"col":11,"h":-1,"v":0},{"word":"LINUX","row":1,"col":0,"h":0,"v":1},{"word":"VIRUS","row":6,"col":6,"h":1,"v":-1},{"word":"BLOG","row":7,"col":9,"h":-1,"v":0},{"word":"SAVE","row":5,"col":4,"h":0,"v":1},{"word":"WWW","row":10,"col":3,"h":-1,"v":0},{"word":"BUS","row":6,"col":9,"h":0,"v":-1},{"word":"APP","row":4,"col":7,"h":0,"v":-1}]}