{"rows":10,"cols":10,"words":["COMPRESS","PRIVACY","MONITOR","PROCESS","OFFLINE","WINDOWS","SERVER","WINDOW","SCRIPT","SYNTAX","PAGE","NODE","WWW","ZIP","HUB"],"boardCharacters":[["P","S","Y","N","T","A","X","F","T","P"],["O","I","S","S","E","R","P","M","O","C"],["D","M","Z","E","R","H","W","W","W","W"],["O","O","W","R","C","W","J","K","S","O"],["F","N","I","V","X","O","P","C","G","D"],["F","I","N","E","O","A","R","R","Z","N"],["L","T","D","R","G","I","F","P","H","I"],["I","O","O","E","P","U","Q","U","H","W"],["N","R","W","T","C","G","B","T","N","R"],["E","V","S","Y","C","A","V","I","R","P"]],"wordPlacements":[{"word":"COMPRESS","row":1,"col":9,"h":-1,"v":0},{"word":"PRIVACY","row":9,"col":9,"h":-1,"v":0},{"word":"MONITOR","row":2,"col":1,"h":0,"v":1},{"word":"PROCESS","row":6,"col":7,"h":-1,"v":-1},{"word":"OFFLINE","row":3,"col":0,"h":0,"v":1},{"word":"WINDOWS","row":3,"col":2,"h":0,"v":1},{"word":"SERVER","row":1,"col":3,"h":0,"v":1},{"word":"WINDOW","row":7,"col":9,"h":0,"v":-1},{"word":"SCRIPT","row":3,"col":8,"h":-1,"v":1},{"word":"SYNTAX","row":0,"col":1,"h":1,"v":0},{"word":"PAGE","row":4,"col":6,"h":-1,"v":1},{"word":"NODE","row":8,"col":0,"h":1,"v":-1},{"word":"WWW","row":2,"col":8,"h":-1,"v":0},{"word":"ZIP","row":2,"col":2,"h":-1,"v":-1},{"word":"HUB","row":6,"col":8,"h":-1,"v":1}]}