{"rows":11,"cols":11,"words":["LURKING","PROCESS","ADDRESS","SYNTAX","QWERTY","PIRACY","ANALOG","UPLOAD","DRIVER","TRASH","MEDIA","WORM","PATH","MASK","BLOG","BITE","APP"],"boardCharacters":[["X","H","A","N","A","L","O","G","P","Y","K"],["A","E","T","I","G","U","A","R","V","C","M"],["T","T","O","A","P","W","O","R","M","A","Q"],["N","I","W","L","P","C","L","Z","K","R","N"],["Y","B","O","J","E","R","R","D","S","I","H"],["S","A","P","S","M","E","C","I","A","P","H"],["D","M","S","Y","V","E","G","U","M","Q","S"],["A","P","P","I","U","P","D","O","F","U","A"],["L","U","R","K","I","N","G","I","L","R","R"],["P","D","Y","T","R","E","W","Q","A","B","T"],["F","S","S","E","R","D","D","A","G","N","F"]],"wordPlacements":[{"word":"LURKING","row":8,"col":0,"h":1,"v":0},{"word":"PROCESS","row":0,"col":8,"h":-1,"v":1},{"word":"ADDRESS","row":10,"col":7,"h":-1,"v":0},{"word":"SYNTAX","row":5,"col":0,"h":0,"v":-1},{"word":"QWERTY","row":9,"col":7,"h":-1,"v":0},{"word":"PIRACY","row":5,"col":9,"h":0,"v":-1},{"word":"ANALOG","row":0,"col":2,"h":1,"v":0},{"word":"UPLOAD","row":1,"col":5,"h":-1,"v":1},{"word":"DRIVER","row":9,"col":1,"h":1,"v":-1},{"word":"TRASH","row":9,"col":10,"h":0,"v":-1},{"word":"MEDIA","row":5,"col":4,"h":1,"v":1},{"word":"WORM","row":2,"col":5,"h":1,"v":0},{"word":"PATH","row":3,"col":4,"h":-1,"v":-1},{"word":"MASK","row":6,"col":8,"h":0,"v":-1},{"word":"BLOG","row":9,"col":9,"h":-1,"v":-1},{"word":"BITE","row":4,"col":1,"h":0,"v":-1},{"word":"APP","row":7,"col":0,"h":1,"v":0}]}