{"rows":9,"cols":9,"words":["ZUCCHINI","VINEGAR","SORGHUM","POULTRY","BRANDY","BITTE","JUICE","SUGAR","YEAST","CAKE","RICE","NUTS"],"boardCharacters":[["X","K","R","A","G","E","N","I","V"],["Y","I","N","I","H","C","C","U","Z"],["M","U","H","G","R","O","S","I","Y"],["E","C","I","U","J","Y","F","B","R"],["M","V","C","S","B","E","R","S","T"],["C","F","L","I","Y","A","L","U","L"],["A","B","T","S","N","S","N","G","U"],["K","T","H","D","N","T","T","A","O"],["E","P","Y","N","U","T","S","R","P"]],"wordPlacements":[{"word":"ZUCCHINI","row":1,"col":8,"h":-1,"v":0},{"word":"VINEGAR","row":0,"col":8,"h":-1,"v":0},{"word":"SORGHUM","row":2,"col":6,"h":-1,"v":0},{"word":"POULTRY","row":8,"col":8,"h":0,"v":-1},{"word":"BRANDY","row":3,"col":7,"h":-1,"v":1},{"word":"BITTE","row":4,"col":4,"h":-1,"v":1},{"word":"JUICE","row":3,"col":4,"h":-1,"v":0},{"word":"SUGAR","row":4,"col":7,"h":0,"v":1},{"word":"YEAST","row":3,"col":5,"h":0,"v":1},{"word":"CAKE","row":5,"col":0,"h":0,"v":1},{"word":"RICE","row":3,"col":8,"h":-1,"v":-1},{"word":"NUTS","row":8,"col":3,"h":1,"v":0}]}