{"rows":12,"cols":12,"words":["AVOCADO","OATMEAL","BRISKET","BURRITO","NUTMEG","CASHEW","CAPERS","TOMATO","GRAIN","CREPE","STEAK","JELLY","PEACH","KEBAB","GYRO","BOWL","BEEF","POT","TEA","NUT","FRY"],"boardCharacters":[["A","S","O","T","A","M","O","T","O","Q","G","L"],["E","R","B","O","W","L","K","M","D","B","Z","X"],["T","E","O","M","P","E","V","O","A","R","N","S"],["F","P","H","R","B","P","O","T","C","I","U","T"],["Y","A","H","A","Y","J","M","H","O","S","T","R"],["L","C","B","T","P","G","C","A","V","K","M","M"],["L","T","O","F","F","A","T","P","A","E","E","F"],["E","U","R","F","E","M","C","E","V","T","G","E"],["J","Y","Q","P","E","R","T","V","Z","J","C","E"],["L","X","P","A","E","S","S","T","U","N","U","B"],["W","D","L","P","Y","B","U","R","R","I","T","O"],["M","W","E","H","S","A","C","N","I","A","R","G"]],"wordPlacements":[{"word":"AVOCADO","row":6,"col":8,"h":0,"v":-1},{"word":"OATMEAL","row":4,"col":8,"h":-1,"v":1},{"word":"BRISKET","row":1,"col":9,"h":0,"v":1},{"word":"BURRITO","row":10,"col":5,"h":1,"v":0},{"word":"NUTMEG","row":2,"col":10,"h":0,"v":1},{"word":"CASHEW","row":11,"col":6,"h":-1,"v":0},{"word":"CAPERS","row":5,"col":1,"h":0,"v":-1},{"word":"TOMATO","row":0,"col":7,"h":-1,"v":0},{"word":"GRAIN","row":11,"col":11,"h":-1,"v":0},{"word":"CREPE","row":7,"col":6,"h":-1,"v":1},{"word":"STEAK","row":9,"col":5,"h":1,"v":-1},{"word":"JELLY","row":8,"col":0,"h":0,"v":-1},{"word":"PEACH","row":8,"col":3,"h":1,"v":-1},{"word":"KEBAB","row":1,"col":6,"h":-1,"v":1},{"word":"GYRO","row":5,"col":5,"h":-1,"v":-1},{"word":"BOWL","row":1,"col":2,"h":1,"v":0},{"word":"BEEF","row":9,"col":11,"h":0,"v":-1},{"word":"POT","row":3,"col":5,"h":1,"v":0},{"word":"TEA","row":2,"col":0,"h":0,"v":-1},{"word":"NUT","row":9,"col":9,"h":-1,"v":0},{"word":"FRY","row":6,"col":3,"h":-1,"v":1}]}