{"rows":9,"cols":9,"words":["WALNUT","BUTTER","WAFFLE","SWEETS","SPICE","BITTE","SPICY","JUICE","SWEET","WHEAT","PORK","BOIL","BEEF","MILK","EGG"],"boardCharacters":[["F","E","E","B","S","P","I","C","Y"],["S","T","E","U","G","I","Y","K","W"],["W","E","C","T","G","C","L","A","B"],["E","E","I","T","E","I","L","O","W"],["E","W","U","E","M","N","I","I","A"],["T","S","J","R","U","L","V","H","F"],["S","L","Q","T","A","E","H","W","F"],["X","R","F","B","I","T","T","E","L"],["P","O","R","K","S","P","I","C","E"]],"wordPlacements":[{"word":"WALNUT","row":1,"col":8,"h":-1,"v":1},{"word":"BUTTER","row":0,"col":3,"h":0,"v":1},{"word":"WAFFLE","row":3,"col":8,"h":0,"v":1},{"word":"SWEETS","row":1,"col":0,"h":0,"v":1},{"word":"SPICE","row":8,"col":4,"h":1,"v":0},{"word":"BITTE","row":7,"col":3,"h":1,"v":0},{"word":"SPICY","row":0,"col":4,"h":1,"v":0},{"word":"JUICE","row":5,"col":2,"h":0,"v":-1},{"word":"SWEET","row":5,"col":1,"h":0,"v":-1},{"word":"WHEAT","row":6,"col":7,"h":-1,"v":0},{"word":"PORK","row":8,"col":0,"h":1,"v":0},{"word":"BOIL","row":2,"col":8,"h":-1,"v":1},{"word":"BEEF","row":0,"col":3,"h":-1,"v":0},{"word":"MILK","row":4,"col":4,"h":1,"v":-1},{"word":"EGG","row":3,"col":4,"h":0,"v":-1}]}