{"rows":6,"cols":6,"words":["SKEIN","STONE","GROSS","POUND","OCTAD","MOLE","LIER"],"boardCharacters":[["G","R","O","S","S","S"],["P","R","Y","H","K","T"],["O","X","E","E","W","O"],["U","U","I","I","T","N"],["N","N","M","O","L","E"],["D","D","A","T","C","O"]],"wordPlacements":[{"word":"SKEIN","row":0,"col":5,"h":-1,"v":1},{"word":"STONE","row":0,"col":5,"h":0,"v":1},{"word":"GROSS","row":0,"col":0,"h":1,"v":0},{"word":"POUND","row":1,"col":0,"h":0,"v":1},{"word":"OCTAD","row":5,"col":5,"h":-1,"v":0},{"word":"MOLE","row":4,"col":2,"h":1,"v":0},{"word":"LIER","row":4,"col":4,"h":-1,"v":-1}]}