{"rows":6,"cols":6,"words":["SHACK","ABBEY","CABIN","YURT","MILL","BARN","GYM"],"boardCharacters":[["M","B","N","S","A","N"],["Y","Y","P","H","B","I"],["U","B","G","A","B","B"],["R","A","R","C","E","A"],["T","N","S","K","Y","C"],["I","L","L","I","M","P"]],"wordPlacements":[{"word":"SHACK","row":0,"col":3,"h":0,"v":1},{"word":"ABBEY","row":0,"col":4,"h":0,"v":1},{"word":"CABIN","row":4,"col":5,"h":0,"v":-1},{"word":"YURT","row":1,"col":0,"h":0,"v":1},{"word":"MILL","row":5,"col":4,"h":-1,"v":0},{"word":"BARN","row":1,"col":4,"h":-1,"v":1},{"word":"GYM","row":2,"col":2,"h":-1,"v":-1}]}