{"rows":9,"cols":9,"words":["GRANARY","HANGAR","SKYWAY","ARMORY","GARAGE","BUNKER","MARKET","MARINA","CEMENT","MANSE","YURT","HALL"],"boardCharacters":[["Y","M","Q","E","G","A","R","A","G"],["Y","G","A","R","M","O","R","Y","N"],["M","R","D","R","L","L","A","H","N"],["A","A","M","U","I","W","C","R","R"],["R","N","Z","A","Y","N","Y","A","E"],["K","A","C","K","N","U","A","G","K"],["E","R","S","G","R","S","P","N","N"],["T","Y","L","T","G","K","E","A","U"],["C","C","E","M","E","N","T","H","B"]],"wordPlacements":[{"word":"GRANARY","row":1,"col":1,"h":0,"v":1},{"word":"HANGAR","row":8,"col":7,"h":0,"v":-1},{"word":"SKYWAY","row":6,"col":2,"h":1,"v":-1},{"word":"ARMORY","row":1,"col":2,"h":1,"v":0},{"word":"GARAGE","row":0,"col":8,"h":-1,"v":0},{"word":"BUNKER","row":8,"col":8,"h":0,"v":-1},{"word":"MARKET","row":2,"col":0,"h":0,"v":1},{"word":"MARINA","row":0,"col":1,"h":1,"v":1},{"word":"CEMENT","row":8,"col":1,"h":1,"v":0},{"word":"MANSE","row":3,"col":2,"h":1,"v":1},{"word":"YURT","row":4,"col":6,"h":-1,"v":1},{"word":"HALL","row":2,"col":7,"h":-1,"v":0}]}