{"rows":9,"cols":9,"words":["MONUMENT","PYRAMID","MINARET","STATION","CASTLE","PAGODA","MOSQUE","HOSTEL","STUDIO","TOMB","FORT","TIPI"],"boardCharacters":[["R","M","A","D","O","G","A","P","S"],["F","O","R","T","X","D","K","H","J"],["N","N","M","M","S","I","E","O","I"],["O","U","I","O","T","M","L","S","P"],["I","M","N","S","U","A","T","T","I"],["T","E","A","Q","D","R","S","E","T"],["A","N","R","U","I","Y","A","L","R"],["T","T","E","E","O","P","C","Q","Y"],["S","L","T","G","B","M","O","T","R"]],"wordPlacements":[{"word":"MONUMENT","row":0,"col":1,"h":0,"v":1},{"word":"PYRAMID","row":7,"col":5,"h":0,"v":-1},{"word":"MINARET","row":2,"col":2,"h":0,"v":1},{"word":"STATION","row":8,"col":0,"h":0,"v":-1},{"word":"CASTLE","row":7,"col":6,"h":0,"v":-1},{"word":"PAGODA","row":0,"col":7,"h":-1,"v":0},{"word":"MOSQUE","row":2,"col":3,"h":0,"v":1},{"word":"HOSTEL","row":1,"col":7,"h":0,"v":1},{"word":"STUDIO","row":2,"col":4,"h":0,"v":1},{"word":"TOMB","row":8,"col":7,"h":-1,"v":0},{"word":"FORT","row":1,"col":0,"h":1,"v":0},{"word":"TIPI","row":5,"col":8,"h":0,"v":-1}]}