{"rows":13,"cols":13,"words":["GUATEMALA","BOTSWANA","ZIMBABWE","TANZANIA","MONGOLIA","MALAYSIA","ANDORRA","BAHAMAS","MOROCCO","BELGIUM","BOLIVIA","ALGERIA","MALAWI","SWEDEN","GUINEA","BENIN","NAURU","SUDAN","MALI","OMAN"],"boardCharacters":[["A","E","N","I","U","G","H","W","K","S","H","A","T"],["E","O","Z","P","B","A","I","N","A","Z","N","A","T"],["W","A","L","A","M","E","T","A","U","G","Y","M","H"],["B","A","R","R","O","D","N","A","R","B","E","O","J"],["A","A","U","R","U","A","N","I","M","E","B","R","Y"],["B","L","M","M","A","P","O","B","N","L","O","O","B"],["M","G","O","A","J","S","O","I","S","G","L","C","A"],["I","E","E","L","L","T","U","W","D","I","I","C","H"],["Z","R","J","A","S","I","E","D","P","U","V","O","A"],["N","I","T","W","N","D","M","G","A","M","I","A","M"],["T","A","A","I","E","Q","C","C","Z","N","A","V","A"],["C","N","M","N","A","I","S","Y","A","L","A","M","S"],["A","B","H","O","X","A","I","L","O","G","N","O","M"]],"wordPlacements":[{"word":"GUATEMALA","row":2,"col":9,"h":-1,"v":0},{"word":"BOTSWANA","row":5,"col":7,"h":-1,"v":1},{"word":"ZIMBABWE","row":8,"col":0,"h":0,"v":-1},{"word":"TANZANIA","row":1,"col":12,"h":-1,"v":0},{"word":"MONGOLIA","row":12,"col":12,"h":-1,"v":0},{"word":"MALAYSIA","row":11,"col":11,"h":-1,"v":0},{"word":"ANDORRA","row":3,"col":7,"h":-1,"v":0},{"word":"BAHAMAS","row":5,"col":12,"h":0,"v":1},{"word":"MOROCCO","row":2,"col":11,"h":0,"v":1},{"word":"BELGIUM","row":3,"col":9,"h":0,"v":1},{"word":"BOLIVIA","row":4,"col":10,"h":0,"v":1},{"word":"ALGERIA","row":4,"col":1,"h":0,"v":1},{"word":"MALAWI","row":5,"col":3,"h":0,"v":1},{"word":"SWEDEN","row":6,"col":8,"h":-1,"v":1},{"word":"GUINEA","row":0,"col":5,"h":-1,"v":0},{"word":"BENIN","row":1,"col":4,"h":1,"v":1},{"word":"NAURU","row":4,"col":6,"h":-1,"v":0},{"word":"SUDAN","row":6,"col":5,"h":1,"v":1},{"word":"MALI","row":5,"col":2,"h":1,"v":1},{"word":"OMAN","row":12,"col":3,"h":-1,"v":-1}]}