{"rows":13,"cols":13,"words":["STROLLER","MOTORCAR","RICKSHAW","AIRCRAFT","JOURNEY","WARNING","TRACKS","HUMVEE","OXCART","ROCKET","PILOT","ROVER","TRUCK","VESPA","STEER","HULL","RIDE","AUTO","YAWL","TIRE","PUNT","SST","SUV"],"boardCharacters":[["M","V","T","R","U","C","K","K","M","O","Z","L","R"],["P","K","U","X","C","B","I","Y","E","X","W","D","T"],["H","J","S","S","M","O","T","O","R","C","A","R","F"],["U","O","K","T","S","S","T","J","I","A","H","E","A"],["M","U","S","S","Q","U","H","L","T","R","S","D","R"],["V","R","T","R","A","F","P","U","N","T","K","I","C"],["E","N","E","V","E","S","T","U","L","U","C","R","R"],["E","E","E","R","E","L","K","O","R","L","I","H","I"],["T","Y","R","B","W","S","L","C","L","E","R","J","A"],["H","Y","K","A","L","A","P","O","A","I","V","A","W"],["V","G","Y","I","Y","N","P","A","R","R","P","O","W"],["W","A","R","N","I","N","G","C","S","T","T","P","R"],["O","T","E","K","C","O","R","B","Z","E","S","I","X"]],"wordPlacements":[{"word":"STROLLER","row":12,"col":10,"h":-1,"v":-1},{"word":"MOTORCAR","row":2,"col":4,"h":1,"v":0},{"word":"RICKSHAW","row":8,"col":10,"h":0,"v":-1},{"word":"AIRCRAFT","row":8,"col":12,"h":0,"v":-1},{"word":"JOURNEY","row":2,"col":1,"h":0,"v":1},{"word":"WARNING","row":11,"col":0,"h":1,"v":0},{"word":"TRACKS","row":11,"col":10,"h":-1,"v":-1},{"word":"HUMVEE","row":2,"col":0,"h":0,"v":1},{"word":"OXCART","row":0,"col":9,"h":0,"v":1},{"word":"ROCKET","row":12,"col":6,"h":-1,"v":0},{"word":"PILOT","row":10,"col":10,"h":-1,"v":-1},{"word":"ROVER","row":11,"col":12,"h":-1,"v":-1},{"word":"TRUCK","row":0,"col":2,"h":1,"v":0},{"word":"VESPA","row":6,"col":3,"h":1,"v":1},{"word":"STEER","row":4,"col":2,"h":0,"v":1},{"word":"HULL","row":4,"col":6,"h":1,"v":1},{"word":"RIDE","row":6,"col":11,"h":0,"v":-1},{"word":"AUTO","row":5,"col":4,"h":1,"v":-1},{"word":"YAWL","row":10,"col":2,"h":1,"v":-1},{"word":"TIRE","row":4,"col":8,"h":0,"v":-1},{"word":"PUNT","row":5,"col":6,"h":1,"v":0},{"word":"SST","row":3,"col":5,"h":-1,"v":0},{"word":"SUV","row":2,"col":3,"h":-1,"v":-1}]}