{"rows":8,"cols":8,"words":["GENERAL","SERVICE","THEATER","ENSIGN","VOLLEY","SQUAD","ENEMY","TANK","STAR"],"boardCharacters":[["E","T","H","E","A","T","E","R"],["C","D","D","N","T","Z","Q","Y"],["I","S","A","E","D","G","G","E"],["V","X","U","M","J","H","V","L"],["R","U","Q","Y","K","F","B","L"],["E","N","S","I","G","N","B","O"],["S","R","A","T","S","L","A","V"],["L","A","R","E","N","E","G","T"]],"wordPlacements":[{"word":"GENERAL","row":7,"col":6,"h":-1,"v":0},{"word":"SERVICE","row":6,"col":0,"h":0,"v":-1},{"word":"THEATER","row":0,"col":1,"h":1,"v":0},{"word":"ENSIGN","row":5,"col":0,"h":1,"v":0},{"word":"VOLLEY","row":6,"col":7,"h":0,"v":-1},{"word":"SQUAD","row":5,"col":2,"h":0,"v":-1},{"word":"ENEMY","row":0,"col":3,"h":0,"v":1},{"word":"TANK","row":7,"col":7,"h":-1,"v":-1},{"word":"STAR","row":6,"col":4,"h":-1,"v":0}]}