{"rows":6,"cols":6,"words":["ENEMY","UNCLE","CLOSE","MARRY","AUNT","GOOD","BOSS"],"boardCharacters":[["M","A","R","R","Y","B"],["E","T","H","E","O","U"],["N","N","Q","S","G","N"],["E","U","S","O","T","C"],["M","A","O","L","T","L"],["Y","D","Y","C","L","E"]],"wordPlacements":[{"word":"ENEMY","row":1,"col":0,"h":0,"v":1},{"word":"UNCLE","row":1,"col":5,"h":0,"v":1},{"word":"CLOSE","row":5,"col":3,"h":0,"v":-1},{"word":"MARRY","row":0,"col":0,"h":1,"v":0},{"word":"AUNT","row":4,"col":1,"h":0,"v":-1},{"word":"GOOD","row":2,"col":4,"h":-1,"v":1},{"word":"BOSS","row":0,"col":5,"h":-1,"v":1}]}